MANIFEST.in
os.path2.pth
setup.py
os.path2.egg-info/PKG-INFO
os.path2.egg-info/SOURCES.txt
os.path2.egg-info/dependency_links.txt
os.path2.egg-info/not-zip-safe
os.path2.egg-info/top_level.txt
path2/__init__.py