Metadata-Version: 1.1
Name: os.path2
Version: 0.0.1
Summary: The os.path module replacement, with simple API.
Home-page: https://github.com/xando/osome
Author: Sebastian Pawluś
Author-email: sebastian.pawlus@gmail.com
License: UNKNOWN
Keywords: os path
Platform: any
Classifier: Development Status :: 4 - Beta
Classifier: Intended Audience :: Developers
Classifier: License :: OSI Approved :: BSD License
Classifier: Operating System :: OS Independent
Classifier: Programming Language :: Python
Classifier: Programming Language :: Python :: 2.6
Classifier: Programming Language :: Python :: 2.7
Classifier: Programming Language :: Python :: 3.3
Classifier: Programming Language :: Python :: Implementation :: PyPy
